[
  {
    "field1": "value1-1",
    "field2": "value2-1",
    "field3": "value3-1"
  },
  {
    "field1": "value1-2",
    "field2": "value2-2",
    "field3": "value3-2"
  },
  {
    "field1": "value1-3",
    "field2": "value2-3",
    "field3": "value3-3"
  },
  {
    "field1": "value1-4",
    "field2": "value2-4",
    "field3": "value3-4"
  },
  {
    "field1": "value1-5",
    "field2": "value2-5",
    "field3": "value3-5"
  },
  {
    "field1": "value1-6",
    "field2": "value2-6",
    "field3": "value3-6"
  },
  {
    "field1": "value1-7",
    "field2": "value2-7",
    "field3": "value3-7"
  },
  {
    "field1": "value1-8",
    "field2": "value2-8",
    "field3": "value3-8"
  },
  {
    "field1": "value1-9",
    "field2": "value2-9",
    "field3": "value3-9"
  },
  {
    "field1": "value1-10",
    "field2": "value2-10",
    "field3": "value3-10"
  },
  {
    "field1": "value1-11",
    "field2": "value2-11",
    "field3": "value3-11"
  },
  {
    "field1": "value1-12",
    "field2": "value2-12",
    "field3": "value3-12"
  },
  {
    "field1": "value1-13",
    "field2": "value2-13",
    "field3": "value3-13"
  },
  {
    "field1": "value1-14",
    "field2": "value2-14",
    "field3": "value3-14"
  },
  {
    "field1": "value1-15",
    "field2": "value2-15",
    "field3": "value3-15"
  },
  {
    "field1": "value1-16",
    "field2": "value2-16",
    "field3": "value3-16"
  },
  {
    "field1": "value1-17",
    "field2": "value2-17",
    "field3": "value3-17"
  },
  {
    "field1": "value1-18",
    "field2": "value2-18",
    "field3": "value3-18"
  },
  {
    "field1": "value1-19",
    "field2": "value2-19",
    "field3": "value3-19"
  },
  {
    "field1": "value1-20",
    "field2": "value2-20",
    "field3": "value3-20"
  },
  {
    "field1": "value1-21",
    "field2": "value2-21",
    "field3": "value3-21"
  },
  {
    "field1": "value1-22",
    "field2": "value2-22",
    "field3": "value3-22"
  },
  {
    "field1": "value1-23",
    "field2": "value2-23",
    "field3": "value3-23"
  },
  {
    "field1": "value1-24",
    "field2": "value2-24",
    "field3": "value3-24"
  },
  {
    "field1": "value1-25",
    "field2": "value2-25",
    "field3": "value3-25"
  },
  {
    "field1": "value1-26",
    "field2": "value2-26",
    "field3": "value3-26"
  },
  {
    "field1": "value1-27",
    "field2": "value2-27",
    "field3": "value3-27"
  },
  {
    "field1": "value1-28",
    "field2": "value2-28",
    "field3": "value3-28"
  },
  {
    "field1": "value1-29",
    "field2": "value2-29",
    "field3": "value3-29"
  },
  {
    "field1": "value1-30",
    "field2": "value2-30",
    "field3": "value3-30"
  },
  {
    "field1": "value1-31",
    "field2": "value2-31",
    "field3": "value3-31"
  },
  {
    "field1": "value1-32",
    "field2": "value2-32",
    "field3": "value3-32"
  },
  {
    "field1": "value1-33",
    "field2": "value2-33",
    "field3": "value3-33"
  },
  {
    "field1": "value1-34",
    "field2": "value2-34",
    "field3": "value3-34"
  },
  {
    "field1": "value1-35",
    "field2": "value2-35",
    "field3": "value3-35"
  },
  {
    "field1": "value1-36",
    "field2": "value2-36",
    "field3": "value3-36"
  },
  {
    "field1": "value1-37",
    "field2": "value2-37",
    "field3": "value3-37"
  },
  {
    "field1": "value1-38",
    "field2": "value2-38",
    "field3": "value3-38"
  },
  {
    "field1": "value1-39",
    "field2": "value2-39",
    "field3": "value3-39"
  },
  {
    "field1": "value1-40",
    "field2": "value2-40",
    "field3": "value3-40"
  },
  {
    "field1": "value1-41",
    "field2": "value2-41",
    "field3": "value3-41"
  },
  {
    "field1": "value1-42",
    "field2": "value2-42",
    "field3": "value3-42"
  },
  {
    "field1": "value1-43",
    "field2": "value2-43",
    "field3": "value3-43"
  },
  {
    "field1": "value1-44",
    "field2": "value2-44",
    "field3": "value3-44"
  },
  {
    "field1": "value1-45",
    "field2": "value2-45",
    "field3": "value3-45"
  },
  {
    "field1": "value1-46",
    "field2": "value2-46",
    "field3": "value3-46"
  },
  {
    "field1": "value1-47",
    "field2": "value2-47",
    "field3": "value3-47"
  },
  {
    "field1": "value1-48",
    "field2": "value2-48",
    "field3": "value3-48"
  },
  {
    "field1": "value1-49",
    "field2": "value2-49",
    "field3": "value3-49"
  },
  {
    "field1": "value1-50",
    "field2": "value2-50",
    "field3": "value3-50"
  },
  {
    "field1": "value1-51",
    "field2": "value2-51",
    "field3": "value3-51"
  },
  {
    "field1": "value1-52",
    "field2": "value2-52",
    "field3": "value3-52"
  },
  {
    "field1": "value1-53",
    "field2": "value2-53",
    "field3": "value3-53"
  },
  {
    "field1": "value1-54",
    "field2": "value2-54",
    "field3": "value3-54"
  },
  {
    "field1": "value1-55",
    "field2": "value2-55",
    "field3": "value3-55"
  },
  {
    "field1": "value1-56",
    "field2": "value2-56",
    "field3": "value3-56"
  },
  {
    "field1": "value1-57",
    "field2": "value2-57",
    "field3": "value3-57"
  },
  {
    "field1": "value1-58",
    "field2": "value2-58",
    "field3": "value3-58"
  },
  {
    "field1": "value1-59",
    "field2": "value2-59",
    "field3": "value3-59"
  },
  {
    "field1": "value1-60",
    "field2": "value2-60",
    "field3": "value3-60"
  },
  {
    "field1": "value1-61",
    "field2": "value2-61",
    "field3": "value3-61"
  },
  {
    "field1": "value1-62",
    "field2": "value2-62",
    "field3": "value3-62"
  },
  {
    "field1": "value1-63",
    "field2": "value2-63",
    "field3": "value3-63"
  },
  {
    "field1": "value1-64",
    "field2": "value2-64",
    "field3": "value3-64"
  },
  {
    "field1": "value1-65",
    "field2": "value2-65",
    "field3": "value3-65"
  },
  {
    "field1": "value1-66",
    "field2": "value2-66",
    "field3": "value3-66"
  },
  {
    "field1": "value1-67",
    "field2": "value2-67",
    "field3": "value3-67"
  },
  {
    "field1": "value1-68",
    "field2": "value2-68",
    "field3": "value3-68"
  },
  {
    "field1": "value1-69",
    "field2": "value2-69",
    "field3": "value3-69"
  },
  {
    "field1": "value1-70",
    "field2": "value2-70",
    "field3": "value3-70"
  },
  {
    "field1": "value1-71",
    "field2": "value2-71",
    "field3": "value3-71"
  },
  {
    "field1": "value1-72",
    "field2": "value2-72",
    "field3": "value3-72"
  },
  {
    "field1": "value1-73",
    "field2": "value2-73",
    "field3": "value3-73"
  },
  {
    "field1": "value1-74",
    "field2": "value2-74",
    "field3": "value3-74"
  },
  {
    "field1": "value1-75",
    "field2": "value2-75",
    "field3": "value3-75"
  },
  {
    "field1": "value1-76",
    "field2": "value2-76",
    "field3": "value3-76"
  },
  {
    "field1": "value1-77",
    "field2": "value2-77",
    "field3": "value3-77"
  },
  {
    "field1": "value1-78",
    "field2": "value2-78",
    "field3": "value3-78"
  },
  {
    "field1": "value1-79",
    "field2": "value2-79",
    "field3": "value3-79"
  },
  {
    "field1": "value1-80",
    "field2": "value2-80",
    "field3": "value3-80"
  },
  {
    "field1": "value1-81",
    "field2": "value2-81",
    "field3": "value3-81"
  },
  {
    "field1": "value1-82",
    "field2": "value2-82",
    "field3": "value3-82"
  },
  {
    "field1": "value1-83",
    "field2": "value2-83",
    "field3": "value3-83"
  },
  {
    "field1": "value1-84",
    "field2": "value2-84",
    "field3": "value3-84"
  },
  {
    "field1": "value1-85",
    "field2": "value2-85",
    "field3": "value3-85"
  },
  {
    "field1": "value1-86",
    "field2": "value2-86",
    "field3": "value3-86"
  },
  {
    "field1": "value1-87",
    "field2": "value2-87",
    "field3": "value3-87"
  },
  {
    "field1": "value1-88",
    "field2": "value2-88",
    "field3": "value3-88"
  },
  {
    "field1": "value1-89",
    "field2": "value2-89",
    "field3": "value3-89"
  },
  {
    "field1": "value1-90",
    "field2": "value2-90",
    "field3": "value3-90"
  },
  {
    "field1": "value1-91",
    "field2": "value2-91",
    "field3": "value3-91"
  },
  {
    "field1": "value1-92",
    "field2": "value2-92",
    "field3": "value3-92"
  },
  {
    "field1": "value1-93",
    "field2": "value2-93",
    "field3": "value3-93"
  },
  {
    "field1": "value1-94",
    "field2": "value2-94",
    "field3": "value3-94"
  },
  {
    "field1": "value1-95",
    "field2": "value2-95",
    "field3": "value3-95"
  },
  {
    "field1": "value1-96",
    "field2": "value2-96",
    "field3": "value3-96"
  },
  {
    "field1": "value1-97",
    "field2": "value2-97",
    "field3": "value3-97"
  },
  {
    "field1": "value1-98",
    "field2": "value2-98",
    "field3": "value3-98"
  },
  {
    "field1": "value1-99",
    "field2": "value2-99",
    "field3": "value3-99"
  },
  {
    "field1": "value1-100",
    "field2": "value2-100",
    "field3": "value3-100"
  }
]